README.txt
setup.cfg
setup.py
mehmood/__init__.py
mehmood.egg-info/PKG-INFO
mehmood.egg-info/SOURCES.txt
mehmood.egg-info/dependency_links.txt
mehmood.egg-info/entry_points.txt
mehmood.egg-info/top_level.txt
mehmood.egg-info/zip-safe