Metadata-Version: 1.0
Name: mehmood
Version: 0.1dev
Summary: Python course 2013, Scilifelab
Home-page: http://www.csc.kth.se/~malagori/
Author: Mehmood Khan
Author-email: malagori@kth.se
License: MIT
Keywords: just testing
Platform: UNKNOWN
